{"_id":"YPV9zOCQ3trpmSdy","name":"(MI) Welcoming - Island Leader","permission":{"default":0,"fKShf9sFzL9Lwpkr":3},"folder":"0Gik9ptGGWKzYonn","sort":100000,"flags":{},"img":"icons/svg/d20-grey.svg","description":"","results":[{"_id":"XpVYL7KZzQHNgqhB","flags":{},"type":0,"text":"Bard (see appendix C)","img":"icons/svg/d20-black.svg","resultId":"","weight":1,"range":[1,1],"drawn":false},{"_id":"n1ISsZV0hXc5rZgp","flags":{},"type":0,"text":"Druid","img":"icons/svg/d20-black.svg","resultId":"","weight":1,"range":[2,2],"drawn":false},{"_id":"SC7Qh3UuqgvwzDGl","flags":{},"type":0,"text":"Guardian naga","img":"icons/svg/d20-black.svg","resultId":"","weight":1,"range":[3,3],"drawn":false},{"_id":"w8iFRTgNcLw2KDMq","flags":{},"type":0,"text":"Treant","img":"icons/svg/d20-black.svg","resultId":"","weight":1,"range":[4,4],"drawn":false},{"_id":"Q4i8EcT2YWYO3gZK","flags":{},"type":0,"text":"Unicorn","img":"icons/svg/d20-black.svg","resultId":"","weight":1,"range":[5,5],"drawn":false},{"_id":"3ZBqgcxxvWbVvntK","flags":{},"type":1,"text":"Dragon Age","img":"icons/svg/d20-black.svg","collection":"RollTable","resultId":"uXDlGnP8ZEJ7n2wX","weight":1,"range":[6,6],"drawn":false},{"_id":"rctC0EoahYmHimSW","flags":{},"type":1,"text":"Metallic Dragon","img":"icons/svg/d20-black.svg","collection":"RollTable","resultId":"4FWarWmpWfGoBQYW","weight":1,"range":[6,6],"drawn":false}],"formula":"1d6","replacement":true,"displayRoll":true}