{"_id":"4QJVfPodSQi2NZoT","name":"(Sandbar) Difficulty Class","permission":{"default":0,"fKShf9sFzL9Lwpkr":3},"folder":"b3TMws0lbuo1sDFs","sort":100000,"flags":{"exportSource":{"world":"toril","system":"dnd5e","coreVersion":"0.6.6","systemVersion":0.96}},"img":"icons/svg/d20-grey.svg","description":"","results":[{"_id":"Z8rsGlClwGsNZHDQ","flags":{},"type":0,"text":"<h2>SANDBAR</h2> <p><b>Type</b></p> <p>Shallow Sandbar</p>  <p><b>Dimensions</b></p> <p>Length: [[1d316 * 10]]</p> <p>Width: [[1d316 * 10]]</p>  <p><b>Diffculty Classes</b></p> <p> DC 12 - passive Wisdom (Perception) to notice</p>  <p> DC 20 - Dexterity saving throw to avoid</p>  <p> DC 20 - ship Strength check to get unstuck</p>","img":"icons/svg/d20-black.svg","resultId":"","weight":1,"range":[1,1],"drawn":false},{"_id":"G2ZOahQqnxSmMxSJ","flags":{},"type":0,"text":"<h2>SANDBAR</h2> <p><b>Type</b></p> <p>Moderate Sandbar</p>  <p><b>Dimensions</b></p> <p>Length: [[1d316 * 10]]</p> <p>Width: [[1d316 * 10]]</p>  <p><b>Diffculty Classes</b></p>  <p> DC 14 - passive Wisdom (Perception) to notice and avoid</p>  <p> DC 15 - Dexterity saving throw zv</p>  <p> DC 15 - ship Strength check to get unstuck</p>","img":"icons/svg/d20-black.svg","resultId":"","weight":4,"range":[2,5],"drawn":false},{"_id":"5u3bsxsFvvj8ftyA","flags":{},"type":0,"text":"<h2>SANDBAR</h2> <p><b>Type</b></p> <p>Deep Sandbar</p>  <p><b>Dimensions</b></p> <p>Length: [[1d316 * 10]]</p> <p>Width: [[1d316 * 10]]</p>  <p><b>Diffculty Classes</b></p> <p> DC 16 - passive Wisdom (Perception) to notice and avoid</p>  <p> DC 10 - Dexterity saving throw to avoid</p>  <p> DC 10 - ship Strength check to get unstuck</p>","img":"icons/svg/d20-black.svg","resultId":"","weight":15,"range":[6,20],"drawn":false}],"formula":"1d20","replacement":true,"displayRoll":true}