{"_id":"WaNHvR7IMM9g5l0u","name":"Mountain (Levels 11-16)","permission":{"default":0,"fKShf9sFzL9Lwpkr":3},"folder":"eP4cPev0ZTI9NM5J","sort":300000,"flags":{},"img":"icons/svg/d20-grey.svg","description":"","results":[{"_id":"YiW0xFdXVXDljuyy","flags":{},"type":0,"text":"[[1d8+1]] basilisks","img":"icons/svg/d20-black.svg","resultId":"","weight":2,"range":[1,2],"drawn":false},{"_id":"XphHBtu7Sj2xPTup","flags":{},"type":0,"text":"[[2d4]] hell hounds","img":"icons/svg/d20-black.svg","resultId":"","weight":2,"range":[3,4],"drawn":false},{"_id":"91iQS34RGLu2MX0d","flags":{},"type":0,"text":"[[1d3]] chimeras","img":"icons/svg/d20-black.svg","resultId":"","weight":2,"range":[5,6],"drawn":false},{"_id":"4PlR805hneqSALix","flags":{},"type":0,"text":"1 galeb duhr","img":"icons/svg/d20-black.svg","resultId":"","weight":2,"range":[7,8],"drawn":false},{"_id":"KnkcCZczfHc2UiCT","flags":{},"type":0,"text":"[[2d6]] veterans","img":"icons/svg/d20-black.svg","resultId":"","weight":2,"range":[9,10],"drawn":false},{"_id":"um0mIyPiRtg0LVHL","flags":{},"type":0,"text":"1 young silver dragon","img":"icons/svg/d20-black.svg","resultId":"","weight":5,"range":[11,15],"drawn":false},{"_id":"TaOpOSWBRSfs0tVV","flags":{},"type":0,"text":"[[2d4]] trolls","img":"icons/svg/d20-black.svg","resultId":"","weight":5,"range":[16,20],"drawn":false},{"_id":"oLnKUHAxNEoqWHYt","flags":{},"type":0,"text":"1 red dragon gliding through the sky above the highest mountaintops","img":"icons/svg/d20-black.svg","resultId":"","weight":5,"range":[21,25],"drawn":false},{"_id":"ldofQCOS05ZGcbLq","flags":{},"type":0,"text":"[[1d8+1]] manticores","img":"icons/svg/d20-black.svg","resultId":"","weight":5,"range":[26,30],"drawn":false},{"_id":"aveKM3ueRwX3k1o0","flags":{},"type":0,"text":"[[1d4]] cyclopes","img":"icons/svg/d20-black.svg","resultId":"","weight":5,"range":[31,35],"drawn":false},{"_id":"eg9482y1bQw3SDEX","flags":{},"type":0,"text":"Heavy snowfall that lasts for [[1d6]] hours","img":"icons/svg/d20-black.svg","resultId":"","weight":5,"range":[36,40],"drawn":false},{"_id":"nIiSioXiJyTX461Y","flags":{},"type":0,"text":"[[1d10]] air elementals","img":"icons/svg/d20-black.svg","resultId":"","weight":5,"range":[41,45],"drawn":false},{"_id":"72cEdQ2MUxghSOYA","flags":{},"type":0,"text":"[[1d6+2]] bulettes","img":"icons/svg/d20-black.svg","resultId":"","weight":5,"range":[46,50],"drawn":false},{"_id":"mkj6C7OFw88jwRId","flags":{},"type":0,"text":"[[1d4]] stone giants","img":"icons/svg/d20-black.svg","resultId":"","weight":5,"range":[51,55],"drawn":false},{"_id":"u5WhTIZq2uJBIUMK","flags":{},"type":0,"text":"1 fire giant","img":"icons/svg/d20-black.svg","resultId":"","weight":5,"range":[56,60],"drawn":false},{"_id":"KRh8Avyqe9UdU4cm","flags":{},"type":0,"text":"2 stone giants playing catch with a boulder a few hundred feet away","img":"icons/svg/d20-black.svg","resultId":"","weight":5,"range":[61,65],"drawn":false},{"_id":"210xOI7y6ul4Sh8Y","flags":{},"type":0,"text":"[[1d8+1]] ettins","img":"icons/svg/d20-black.svg","resultId":"","weight":5,"range":[66,70],"drawn":false},{"_id":"lKSj0pJLgtKpWEod","flags":{},"type":0,"text":"[[1d3]] frost giants","img":"icons/svg/d20-black.svg","resultId":"","weight":5,"range":[71,75],"drawn":false},{"_id":"8qpSIAz4WozurwoS","flags":{},"type":0,"text":"A wide crevasse, its depths shrouded in mist","img":"icons/svg/d20-black.svg","resultId":"","weight":5,"range":[76,80],"drawn":false},{"_id":"Zal9jtTQfrbBJWlm","flags":{},"type":0,"text":"[[1d4]] cloud giants","img":"icons/svg/d20-black.svg","resultId":"","weight":5,"range":[81,85],"drawn":false},{"_id":"0RmkC8iPNEVrxWuW","flags":{},"type":0,"text":"1 adult silver dragon","img":"icons/svg/d20-black.svg","resultId":"","weight":5,"range":[86,90],"drawn":false},{"_id":"dVm4YnpD43dUzUZJ","flags":{},"type":0,"text":"1 adult red dragon","img":"icons/svg/d20-black.svg","resultId":"","weight":6,"range":[91,96],"drawn":false},{"_id":"upDcdAfLh0146jS3","flags":{},"type":0,"text":"[[1d4]] rocs","img":"icons/svg/d20-black.svg","resultId":"","weight":2,"range":[97,98],"drawn":false},{"_id":"ie38YPGVaXpfedwD","flags":{},"type":0,"text":"1 ancient silver dragon","img":"icons/svg/d20-black.svg","resultId":"","weight":1,"range":[99,99],"drawn":false},{"_id":"5fo7L8vXA6U9x1Ny","flags":{},"type":0,"text":"1 ancient red dragon","img":"icons/svg/d20-black.svg","resultId":"","weight":1,"range":[100,100],"drawn":false}],"formula":"1d100","replacement":true,"displayRoll":true}